public class org.mozilla.classfile.ByteCode extends java.lang.Object
{
    public static final int NOP;
    public static final int ACONST_NULL;
    public static final int ICONST_M1;
    public static final int ICONST_0;
    public static final int ICONST_1;
    public static final int ICONST_2;
    public static final int ICONST_3;
    public static final int ICONST_4;
    public static final int ICONST_5;
    public static final int LCONST_0;
    public static final int LCONST_1;
    public static final int FCONST_0;
    public static final int FCONST_1;
    public static final int FCONST_2;
    public static final int DCONST_0;
    public static final int DCONST_1;
    public static final int BIPUSH;
    public static final int SIPUSH;
    public static final int LDC;
    public static final int LDC_W;
    public static final int LDC2_W;
    public static final int ILOAD;
    public static final int LLOAD;
    public static final int FLOAD;
    public static final int DLOAD;
    public static final int ALOAD;
    public static final int ILOAD_0;
    public static final int ILOAD_1;
    public static final int ILOAD_2;
    public static final int ILOAD_3;
    public static final int LLOAD_0;
    public static final int LLOAD_1;
    public static final int LLOAD_2;
    public static final int LLOAD_3;
    public static final int FLOAD_0;
    public static final int FLOAD_1;
    public static final int FLOAD_2;
    public static final int FLOAD_3;
    public static final int DLOAD_0;
    public static final int DLOAD_1;
    public static final int DLOAD_2;
    public static final int DLOAD_3;
    public static final int ALOAD_0;
    public static final int ALOAD_1;
    public static final int ALOAD_2;
    public static final int ALOAD_3;
    public static final int IALOAD;
    public static final int LALOAD;
    public static final int FALOAD;
    public static final int DALOAD;
    public static final int AALOAD;
    public static final int BALOAD;
    public static final int CALOAD;
    public static final int SALOAD;
    public static final int ISTORE;
    public static final int LSTORE;
    public static final int FSTORE;
    public static final int DSTORE;
    public static final int ASTORE;
    public static final int ISTORE_0;
    public static final int ISTORE_1;
    public static final int ISTORE_2;
    public static final int ISTORE_3;
    public static final int LSTORE_0;
    public static final int LSTORE_1;
    public static final int LSTORE_2;
    public static final int LSTORE_3;
    public static final int FSTORE_0;
    public static final int FSTORE_1;
    public static final int FSTORE_2;
    public static final int FSTORE_3;
    public static final int DSTORE_0;
    public static final int DSTORE_1;
    public static final int DSTORE_2;
    public static final int DSTORE_3;
    public static final int ASTORE_0;
    public static final int ASTORE_1;
    public static final int ASTORE_2;
    public static final int ASTORE_3;
    public static final int IASTORE;
    public static final int LASTORE;
    public static final int FASTORE;
    public static final int DASTORE;
    public static final int AASTORE;
    public static final int BASTORE;
    public static final int CASTORE;
    public static final int SASTORE;
    public static final int POP;
    public static final int POP2;
    public static final int DUP;
    public static final int DUP_X1;
    public static final int DUP_X2;
    public static final int DUP2;
    public static final int DUP2_X1;
    public static final int DUP2_X2;
    public static final int SWAP;
    public static final int IADD;
    public static final int LADD;
    public static final int FADD;
    public static final int DADD;
    public static final int ISUB;
    public static final int LSUB;
    public static final int FSUB;
    public static final int DSUB;
    public static final int IMUL;
    public static final int LMUL;
    public static final int FMUL;
    public static final int DMUL;
    public static final int IDIV;
    public static final int LDIV;
    public static final int FDIV;
    public static final int DDIV;
    public static final int IREM;
    public static final int LREM;
    public static final int FREM;
    public static final int DREM;
    public static final int INEG;
    public static final int LNEG;
    public static final int FNEG;
    public static final int DNEG;
    public static final int ISHL;
    public static final int LSHL;
    public static final int ISHR;
    public static final int LSHR;
    public static final int IUSHR;
    public static final int LUSHR;
    public static final int IAND;
    public static final int LAND;
    public static final int IOR;
    public static final int LOR;
    public static final int IXOR;
    public static final int LXOR;
    public static final int IINC;
    public static final int I2L;
    public static final int I2F;
    public static final int I2D;
    public static final int L2I;
    public static final int L2F;
    public static final int L2D;
    public static final int F2I;
    public static final int F2L;
    public static final int F2D;
    public static final int D2I;
    public static final int D2L;
    public static final int D2F;
    public static final int I2B;
    public static final int I2C;
    public static final int I2S;
    public static final int LCMP;
    public static final int FCMPL;
    public static final int FCMPG;
    public static final int DCMPL;
    public static final int DCMPG;
    public static final int IFEQ;
    public static final int IFNE;
    public static final int IFLT;
    public static final int IFGE;
    public static final int IFGT;
    public static final int IFLE;
    public static final int IF_ICMPEQ;
    public static final int IF_ICMPNE;
    public static final int IF_ICMPLT;
    public static final int IF_ICMPGE;
    public static final int IF_ICMPGT;
    public static final int IF_ICMPLE;
    public static final int IF_ACMPEQ;
    public static final int IF_ACMPNE;
    public static final int GOTO;
    public static final int JSR;
    public static final int RET;
    public static final int TABLESWITCH;
    public static final int LOOKUPSWITCH;
    public static final int IRETURN;
    public static final int LRETURN;
    public static final int FRETURN;
    public static final int DRETURN;
    public static final int ARETURN;
    public static final int RETURN;
    public static final int GETSTATIC;
    public static final int PUTSTATIC;
    public static final int GETFIELD;
    public static final int PUTFIELD;
    public static final int INVOKEVIRTUAL;
    public static final int INVOKESPECIAL;
    public static final int INVOKESTATIC;
    public static final int INVOKEINTERFACE;
    public static final int NEW;
    public static final int NEWARRAY;
    public static final int ANEWARRAY;
    public static final int ARRAYLENGTH;
    public static final int ATHROW;
    public static final int CHECKCAST;
    public static final int INSTANCEOF;
    public static final int MONITORENTER;
    public static final int MONITOREXIT;
    public static final int WIDE;
    public static final int MULTIANEWARRAY;
    public static final int IFNULL;
    public static final int IFNONNULL;
    public static final int GOTO_W;
    public static final int JSR_W;
    public static final int BREAKPOINT;
    public static final int IMPDEP1;
    public static final int IMPDEP2;
    public static final byte T_BOOLEAN;
    public static final byte T_CHAR;
    public static final byte T_FLOAT;
    public static final byte T_DOUBLE;
    public static final byte T_BYTE;
    public static final byte T_SHORT;
    public static final byte T_INT;
    public static final byte T_LONG;

    public void <init>()
    {
        org.mozilla.classfile.ByteCode r0;

        r0 := @this: org.mozilla.classfile.ByteCode;

        specialinvoke r0.<java.lang.Object: void <init>()>();

        return;
    }

    public static void <clinit>()
    {
        <org.mozilla.classfile.ByteCode: byte T_LONG> = 11;

        <org.mozilla.classfile.ByteCode: byte T_INT> = 10;

        <org.mozilla.classfile.ByteCode: byte T_SHORT> = 9;

        <org.mozilla.classfile.ByteCode: byte T_BYTE> = 8;

        <org.mozilla.classfile.ByteCode: byte T_DOUBLE> = 7;

        <org.mozilla.classfile.ByteCode: byte T_FLOAT> = 6;

        <org.mozilla.classfile.ByteCode: byte T_CHAR> = 5;

        <org.mozilla.classfile.ByteCode: byte T_BOOLEAN> = 4;

        <org.mozilla.classfile.ByteCode: int IMPDEP2> = 255;

        <org.mozilla.classfile.ByteCode: int IMPDEP1> = 254;

        <org.mozilla.classfile.ByteCode: int BREAKPOINT> = 202;

        <org.mozilla.classfile.ByteCode: int JSR_W> = 201;

        <org.mozilla.classfile.ByteCode: int GOTO_W> = 200;

        <org.mozilla.classfile.ByteCode: int IFNONNULL> = 199;

        <org.mozilla.classfile.ByteCode: int IFNULL> = 198;

        <org.mozilla.classfile.ByteCode: int MULTIANEWARRAY> = 197;

        <org.mozilla.classfile.ByteCode: int WIDE> = 196;

        <org.mozilla.classfile.ByteCode: int MONITOREXIT> = 195;

        <org.mozilla.classfile.ByteCode: int MONITORENTER> = 194;

        <org.mozilla.classfile.ByteCode: int INSTANCEOF> = 193;

        <org.mozilla.classfile.ByteCode: int CHECKCAST> = 192;

        <org.mozilla.classfile.ByteCode: int ATHROW> = 191;

        <org.mozilla.classfile.ByteCode: int ARRAYLENGTH> = 190;

        <org.mozilla.classfile.ByteCode: int ANEWARRAY> = 189;

        <org.mozilla.classfile.ByteCode: int NEWARRAY> = 188;

        <org.mozilla.classfile.ByteCode: int NEW> = 187;

        <org.mozilla.classfile.ByteCode: int INVOKEINTERFACE> = 185;

        <org.mozilla.classfile.ByteCode: int INVOKESTATIC> = 184;

        <org.mozilla.classfile.ByteCode: int INVOKESPECIAL> = 183;

        <org.mozilla.classfile.ByteCode: int INVOKEVIRTUAL> = 182;

        <org.mozilla.classfile.ByteCode: int PUTFIELD> = 181;

        <org.mozilla.classfile.ByteCode: int GETFIELD> = 180;

        <org.mozilla.classfile.ByteCode: int PUTSTATIC> = 179;

        <org.mozilla.classfile.ByteCode: int GETSTATIC> = 178;

        <org.mozilla.classfile.ByteCode: int RETURN> = 177;

        <org.mozilla.classfile.ByteCode: int ARETURN> = 176;

        <org.mozilla.classfile.ByteCode: int DRETURN> = 175;

        <org.mozilla.classfile.ByteCode: int FRETURN> = 174;

        <org.mozilla.classfile.ByteCode: int LRETURN> = 173;

        <org.mozilla.classfile.ByteCode: int IRETURN> = 172;

        <org.mozilla.classfile.ByteCode: int LOOKUPSWITCH> = 171;

        <org.mozilla.classfile.ByteCode: int TABLESWITCH> = 170;

        <org.mozilla.classfile.ByteCode: int RET> = 169;

        <org.mozilla.classfile.ByteCode: int JSR> = 168;

        <org.mozilla.classfile.ByteCode: int GOTO> = 167;

        <org.mozilla.classfile.ByteCode: int IF_ACMPNE> = 166;

        <org.mozilla.classfile.ByteCode: int IF_ACMPEQ> = 165;

        <org.mozilla.classfile.ByteCode: int IF_ICMPLE> = 164;

        <org.mozilla.classfile.ByteCode: int IF_ICMPGT> = 163;

        <org.mozilla.classfile.ByteCode: int IF_ICMPGE> = 162;

        <org.mozilla.classfile.ByteCode: int IF_ICMPLT> = 161;

        <org.mozilla.classfile.ByteCode: int IF_ICMPNE> = 160;

        <org.mozilla.classfile.ByteCode: int IF_ICMPEQ> = 159;

        <org.mozilla.classfile.ByteCode: int IFLE> = 158;

        <org.mozilla.classfile.ByteCode: int IFGT> = 157;

        <org.mozilla.classfile.ByteCode: int IFGE> = 156;

        <org.mozilla.classfile.ByteCode: int IFLT> = 155;

        <org.mozilla.classfile.ByteCode: int IFNE> = 154;

        <org.mozilla.classfile.ByteCode: int IFEQ> = 153;

        <org.mozilla.classfile.ByteCode: int DCMPG> = 152;

        <org.mozilla.classfile.ByteCode: int DCMPL> = 151;

        <org.mozilla.classfile.ByteCode: int FCMPG> = 150;

        <org.mozilla.classfile.ByteCode: int FCMPL> = 149;

        <org.mozilla.classfile.ByteCode: int LCMP> = 148;

        <org.mozilla.classfile.ByteCode: int I2S> = 147;

        <org.mozilla.classfile.ByteCode: int I2C> = 146;

        <org.mozilla.classfile.ByteCode: int I2B> = 145;

        <org.mozilla.classfile.ByteCode: int D2F> = 144;

        <org.mozilla.classfile.ByteCode: int D2L> = 143;

        <org.mozilla.classfile.ByteCode: int D2I> = 142;

        <org.mozilla.classfile.ByteCode: int F2D> = 141;

        <org.mozilla.classfile.ByteCode: int F2L> = 140;

        <org.mozilla.classfile.ByteCode: int F2I> = 139;

        <org.mozilla.classfile.ByteCode: int L2D> = 138;

        <org.mozilla.classfile.ByteCode: int L2F> = 137;

        <org.mozilla.classfile.ByteCode: int L2I> = 136;

        <org.mozilla.classfile.ByteCode: int I2D> = 135;

        <org.mozilla.classfile.ByteCode: int I2F> = 134;

        <org.mozilla.classfile.ByteCode: int I2L> = 133;

        <org.mozilla.classfile.ByteCode: int IINC> = 132;

        <org.mozilla.classfile.ByteCode: int LXOR> = 131;

        <org.mozilla.classfile.ByteCode: int IXOR> = 130;

        <org.mozilla.classfile.ByteCode: int LOR> = 129;

        <org.mozilla.classfile.ByteCode: int IOR> = 128;

        <org.mozilla.classfile.ByteCode: int LAND> = 127;

        <org.mozilla.classfile.ByteCode: int IAND> = 126;

        <org.mozilla.classfile.ByteCode: int LUSHR> = 125;

        <org.mozilla.classfile.ByteCode: int IUSHR> = 124;

        <org.mozilla.classfile.ByteCode: int LSHR> = 123;

        <org.mozilla.classfile.ByteCode: int ISHR> = 122;

        <org.mozilla.classfile.ByteCode: int LSHL> = 121;

        <org.mozilla.classfile.ByteCode: int ISHL> = 120;

        <org.mozilla.classfile.ByteCode: int DNEG> = 119;

        <org.mozilla.classfile.ByteCode: int FNEG> = 118;

        <org.mozilla.classfile.ByteCode: int LNEG> = 117;

        <org.mozilla.classfile.ByteCode: int INEG> = 116;

        <org.mozilla.classfile.ByteCode: int DREM> = 115;

        <org.mozilla.classfile.ByteCode: int FREM> = 114;

        <org.mozilla.classfile.ByteCode: int LREM> = 113;

        <org.mozilla.classfile.ByteCode: int IREM> = 112;

        <org.mozilla.classfile.ByteCode: int DDIV> = 111;

        <org.mozilla.classfile.ByteCode: int FDIV> = 110;

        <org.mozilla.classfile.ByteCode: int LDIV> = 109;

        <org.mozilla.classfile.ByteCode: int IDIV> = 108;

        <org.mozilla.classfile.ByteCode: int DMUL> = 107;

        <org.mozilla.classfile.ByteCode: int FMUL> = 106;

        <org.mozilla.classfile.ByteCode: int LMUL> = 105;

        <org.mozilla.classfile.ByteCode: int IMUL> = 104;

        <org.mozilla.classfile.ByteCode: int DSUB> = 103;

        <org.mozilla.classfile.ByteCode: int FSUB> = 102;

        <org.mozilla.classfile.ByteCode: int LSUB> = 101;

        <org.mozilla.classfile.ByteCode: int ISUB> = 100;

        <org.mozilla.classfile.ByteCode: int DADD> = 99;

        <org.mozilla.classfile.ByteCode: int FADD> = 98;

        <org.mozilla.classfile.ByteCode: int LADD> = 97;

        <org.mozilla.classfile.ByteCode: int IADD> = 96;

        <org.mozilla.classfile.ByteCode: int SWAP> = 95;

        <org.mozilla.classfile.ByteCode: int DUP2_X2> = 94;

        <org.mozilla.classfile.ByteCode: int DUP2_X1> = 93;

        <org.mozilla.classfile.ByteCode: int DUP2> = 92;

        <org.mozilla.classfile.ByteCode: int DUP_X2> = 91;

        <org.mozilla.classfile.ByteCode: int DUP_X1> = 90;

        <org.mozilla.classfile.ByteCode: int DUP> = 89;

        <org.mozilla.classfile.ByteCode: int POP2> = 88;

        <org.mozilla.classfile.ByteCode: int POP> = 87;

        <org.mozilla.classfile.ByteCode: int SASTORE> = 86;

        <org.mozilla.classfile.ByteCode: int CASTORE> = 85;

        <org.mozilla.classfile.ByteCode: int BASTORE> = 84;

        <org.mozilla.classfile.ByteCode: int AASTORE> = 83;

        <org.mozilla.classfile.ByteCode: int DASTORE> = 82;

        <org.mozilla.classfile.ByteCode: int FASTORE> = 81;

        <org.mozilla.classfile.ByteCode: int LASTORE> = 80;

        <org.mozilla.classfile.ByteCode: int IASTORE> = 79;

        <org.mozilla.classfile.ByteCode: int ASTORE_3> = 78;

        <org.mozilla.classfile.ByteCode: int ASTORE_2> = 77;

        <org.mozilla.classfile.ByteCode: int ASTORE_1> = 76;

        <org.mozilla.classfile.ByteCode: int ASTORE_0> = 75;

        <org.mozilla.classfile.ByteCode: int DSTORE_3> = 74;

        <org.mozilla.classfile.ByteCode: int DSTORE_2> = 73;

        <org.mozilla.classfile.ByteCode: int DSTORE_1> = 72;

        <org.mozilla.classfile.ByteCode: int DSTORE_0> = 71;

        <org.mozilla.classfile.ByteCode: int FSTORE_3> = 70;

        <org.mozilla.classfile.ByteCode: int FSTORE_2> = 69;

        <org.mozilla.classfile.ByteCode: int FSTORE_1> = 68;

        <org.mozilla.classfile.ByteCode: int FSTORE_0> = 67;

        <org.mozilla.classfile.ByteCode: int LSTORE_3> = 66;

        <org.mozilla.classfile.ByteCode: int LSTORE_2> = 65;

        <org.mozilla.classfile.ByteCode: int LSTORE_1> = 64;

        <org.mozilla.classfile.ByteCode: int LSTORE_0> = 63;

        <org.mozilla.classfile.ByteCode: int ISTORE_3> = 62;

        <org.mozilla.classfile.ByteCode: int ISTORE_2> = 61;

        <org.mozilla.classfile.ByteCode: int ISTORE_1> = 60;

        <org.mozilla.classfile.ByteCode: int ISTORE_0> = 59;

        <org.mozilla.classfile.ByteCode: int ASTORE> = 58;

        <org.mozilla.classfile.ByteCode: int DSTORE> = 57;

        <org.mozilla.classfile.ByteCode: int FSTORE> = 56;

        <org.mozilla.classfile.ByteCode: int LSTORE> = 55;

        <org.mozilla.classfile.ByteCode: int ISTORE> = 54;

        <org.mozilla.classfile.ByteCode: int SALOAD> = 53;

        <org.mozilla.classfile.ByteCode: int CALOAD> = 52;

        <org.mozilla.classfile.ByteCode: int BALOAD> = 51;

        <org.mozilla.classfile.ByteCode: int AALOAD> = 50;

        <org.mozilla.classfile.ByteCode: int DALOAD> = 49;

        <org.mozilla.classfile.ByteCode: int FALOAD> = 48;

        <org.mozilla.classfile.ByteCode: int LALOAD> = 47;

        <org.mozilla.classfile.ByteCode: int IALOAD> = 46;

        <org.mozilla.classfile.ByteCode: int ALOAD_3> = 45;

        <org.mozilla.classfile.ByteCode: int ALOAD_2> = 44;

        <org.mozilla.classfile.ByteCode: int ALOAD_1> = 43;

        <org.mozilla.classfile.ByteCode: int ALOAD_0> = 42;

        <org.mozilla.classfile.ByteCode: int DLOAD_3> = 41;

        <org.mozilla.classfile.ByteCode: int DLOAD_2> = 40;

        <org.mozilla.classfile.ByteCode: int DLOAD_1> = 39;

        <org.mozilla.classfile.ByteCode: int DLOAD_0> = 38;

        <org.mozilla.classfile.ByteCode: int FLOAD_3> = 37;

        <org.mozilla.classfile.ByteCode: int FLOAD_2> = 36;

        <org.mozilla.classfile.ByteCode: int FLOAD_1> = 35;

        <org.mozilla.classfile.ByteCode: int FLOAD_0> = 34;

        <org.mozilla.classfile.ByteCode: int LLOAD_3> = 33;

        <org.mozilla.classfile.ByteCode: int LLOAD_2> = 32;

        <org.mozilla.classfile.ByteCode: int LLOAD_1> = 31;

        <org.mozilla.classfile.ByteCode: int LLOAD_0> = 30;

        <org.mozilla.classfile.ByteCode: int ILOAD_3> = 29;

        <org.mozilla.classfile.ByteCode: int ILOAD_2> = 28;

        <org.mozilla.classfile.ByteCode: int ILOAD_1> = 27;

        <org.mozilla.classfile.ByteCode: int ILOAD_0> = 26;

        <org.mozilla.classfile.ByteCode: int ALOAD> = 25;

        <org.mozilla.classfile.ByteCode: int DLOAD> = 24;

        <org.mozilla.classfile.ByteCode: int FLOAD> = 23;

        <org.mozilla.classfile.ByteCode: int LLOAD> = 22;

        <org.mozilla.classfile.ByteCode: int ILOAD> = 21;

        <org.mozilla.classfile.ByteCode: int LDC2_W> = 20;

        <org.mozilla.classfile.ByteCode: int LDC_W> = 19;

        <org.mozilla.classfile.ByteCode: int LDC> = 18;

        <org.mozilla.classfile.ByteCode: int SIPUSH> = 17;

        <org.mozilla.classfile.ByteCode: int BIPUSH> = 16;

        <org.mozilla.classfile.ByteCode: int DCONST_1> = 15;

        <org.mozilla.classfile.ByteCode: int DCONST_0> = 14;

        <org.mozilla.classfile.ByteCode: int FCONST_2> = 13;

        <org.mozilla.classfile.ByteCode: int FCONST_1> = 12;

        <org.mozilla.classfile.ByteCode: int FCONST_0> = 11;

        <org.mozilla.classfile.ByteCode: int LCONST_1> = 10;

        <org.mozilla.classfile.ByteCode: int LCONST_0> = 9;

        <org.mozilla.classfile.ByteCode: int ICONST_5> = 8;

        <org.mozilla.classfile.ByteCode: int ICONST_4> = 7;

        <org.mozilla.classfile.ByteCode: int ICONST_3> = 6;

        <org.mozilla.classfile.ByteCode: int ICONST_2> = 5;

        <org.mozilla.classfile.ByteCode: int ICONST_1> = 4;

        <org.mozilla.classfile.ByteCode: int ICONST_0> = 3;

        <org.mozilla.classfile.ByteCode: int ICONST_M1> = 2;

        <org.mozilla.classfile.ByteCode: int ACONST_NULL> = 1;

        <org.mozilla.classfile.ByteCode: int NOP> = 0;

        return;
    }
}
